{"http://www.w3.org/1999/02/22-rdf-syntax-ns#type": ["http://www.w3.org/2002/07/owl#Class"], "http://www.w3.org/2000/01/rdf-schema#label": ["Brunnen"], "http://www.w3.org/2000/01/rdf-schema#subClassOf": ["http://www.xerleben.de/schema/2.0_1/XE_TechnischesBauwerk"], "http://www.w3.org/2002/07/owl#equivalentClass": ["n8b741e43c80b4a6fb01959f924a44521b1262"], "http://www.w3.org/2004/02/skos/core#definition": ["Brunnen mit besonderer touristischer Bedeutung (i.d.R. Zierbrunnen, ohne Trinkwasserversorgung). "], "http://www.wikidata.org/entity/Property:P18": ["http://www.xerleben.de/signaturen/2.8/standard/svg/22301250_XE_TechnischesBauwerk_Brunnen.svg"], "http://www.xerleben.de/schema/2.0_1/code": ["22301250"], "http://www.xerleben.de/schema/2.0_1/sinceVersion": ["1.0"]}