{"http://www.semgis.de/geodata#propOrder": ["typ"], "http://www.semgis.de/geodata#standard": ["xplanung"], "http://www.w3.org/1999/02/22-rdf-syntax-ns#type": ["http://www.w3.org/2002/07/owl#Class"], "http://www.w3.org/2000/01/rdf-schema#comment": ["Forstwirtschaft ist die zielgerichtete Bewirtschaftung von W\u00e4ldern.\nDie nat\u00fcrlichen Abl\u00e4ufe in den Wald\u00f6kosystemen werden dabei so gestaltet und gesteuert, dass sie einen m\u00f6glichst gro\u00dfen Beitrag zur Erf\u00fcllung von Leistungen erbringen, die von den Waldeigent\u00fcmern und der Gesellschaft gew\u00fcnscht werden."], "http://www.w3.org/2000/01/rdf-schema#label": ["RP_Forstwirtschaft"], "http://www.w3.org/2000/01/rdf-schema#subClassOf": ["http://www.xplanung.de/xplangml/5/0#RP_Freiraum", "nf28aeab5bce54803a9e6c72fc620feeab2131"]}