{"http://www.semgis.de/geodata#propOrder": ["zweckbestimmung;detaillierteZweckbestimmung"], "http://www.semgis.de/geodata#standard": ["xplanung"], "http://www.w3.org/1999/02/22-rdf-syntax-ns#type": ["http://www.w3.org/2002/07/owl#Class"], "http://www.w3.org/2000/01/rdf-schema#comment": ["Darstellung einer Landwirtschaftsfl\u00e4che nach \u00a75, Abs. 2, Nr. 9a."], "http://www.w3.org/2000/01/rdf-schema#label": ["FP_LandwirtschaftsFlaeche"], "http://www.w3.org/2000/01/rdf-schema#subClassOf": ["http://www.xplanung.de/xplangml/5/0#FP_Flaechenschlussobjekt", "n24b7e6772bcd43a5845b01ba9613abcfb1649", "n24b7e6772bcd43a5845b01ba9613abcfb1650"]}