{"http://www.adv-online.de/namespaces/adv/gid/6.0#kennung": ["LFD"], "http://www.w3.org/1999/02/22-rdf-syntax-ns#type": ["http://www.w3.org/2002/07/owl#AnnotationProperty", "http://www.w3.org/2002/07/owl#ObjectProperty", "http://www.w3.org/2002/07/owl#DatatypeProperty"], "http://www.w3.org/2000/01/rdf-schema#domain": ["http://www.adv-online.de/namespaces/adv/gid/6.0#AX_Buchungsstelle", "http://www.adv-online.de/namespaces/adv/gid/6.0#AX_Fortfuehrungsfall", "http://www.adv-online.de/namespaces/adv/gid/6.0#AX_Fortfuehrungsnummer", "http://www.adv-online.de/namespaces/adv/gid/6.0#AX_K_Fortfuehrungsfall_Ausgabe", "http://www.adv-online.de/namespaces/adv/gid/6.0#AX_K_Fortfuehrungsfall_FM", "http://www.adv-online.de/namespaces/adv/gid/6.0#AX_K_Fortfuehrungsfall_FMJ", "http://www.adv-online.de/namespaces/adv/gid/6.0#AX_LagebezeichnungMitPseudonummer", "http://www.adv-online.de/namespaces/adv/gid/6.0#AX_Lagebezeichnung_K_GEBAEUDE", "http://www.adv-online.de/namespaces/adv/gid/6.0#AX_Namensnummer_K_PERS1"], "http://www.w3.org/2000/01/rdf-schema#range": ["http://www.w3.org/2001/XMLSchema#string"], "http://www.w3.org/2000/01/rdf-schema#subPropertyOf": ["http://www.adv-online.de/namespaces/adv/gid/6.0#AAA6"], "http://www.w3.org/2004/02/skos/core#definition": ["Diese Attributart enth\u00e4lt die laufende Nummer des Fortf\u00fchrungsnachweises."]}