{"http://www.w3.org/1999/02/22-rdf-syntax-ns#type": ["http://www.w3.org/2002/07/owl#ObjectProperty", "http://www.w3.org/2002/07/owl#Class"], "http://www.w3.org/2000/01/rdf-schema#label": ["AX_DQMitDatenerhebung"], "http://www.w3.org/2000/01/rdf-schema#range": ["http://www.adv-online.de/namespaces/adv/gid/6.0#AX_DQMitDatenerhebung"], "http://www.w3.org/2000/01/rdf-schema#subClassOf": ["http://www.adv-online.de/namespaces/adv/gid/6.0#AAA6", "http://www.opengis.net/gml/3.2#AbstractObject", "n22435f2eeed4476e9b2ed9a26a976085b2103", "n22435f2eeed4476e9b2ed9a26a976085b2104"], "http://www.w3.org/2000/01/rdf-schema#subPropertyOf": ["http://www.adv-online.de/namespaces/adv/gid/6.0#AAA6", "http://www.opengis.net/gml/3.2#AbstractObject"], "http://www.w3.org/2004/02/skos/core#definition": ["Angaben zur Herkunft der Informationen (Erhebungsstelle). Die Information ist konform zu den Vorgaben aus ISO 19115 zu repr\u00e4sentieren."]}