{"http://www.semgis.de/geodata#propOrder": ["ziel;sonstZiel;massnahme;istAusgleich;refMassnahmenText;refLandschaftsplan"], "http://www.semgis.de/geodata#standard": ["xplanung"], "http://www.w3.org/1999/02/22-rdf-syntax-ns#type": ["http://www.w3.org/2002/07/owl#Class"], "http://www.w3.org/2000/01/rdf-schema#comment": ["Ma\u00dfnahmen zum Schutz, zur Pflege und zur Entwicklung von Natur und Landschaft (\u00a79 Abs. 1 Nr. 20 und Abs. 4 BauGB)."], "http://www.w3.org/2000/01/rdf-schema#label": ["BP_SchutzPflegeEntwicklungsMassnahme"], "http://www.w3.org/2000/01/rdf-schema#subClassOf": ["http://www.xplanung.de/xplangml/5/0#BP_Geometrieobjekt", "nf28aeab5bce54803a9e6c72fc620feeab1273", "nf28aeab5bce54803a9e6c72fc620feeab1274", "nf28aeab5bce54803a9e6c72fc620feeab1275", "nf28aeab5bce54803a9e6c72fc620feeab1276", "nf28aeab5bce54803a9e6c72fc620feeab1277", "nf28aeab5bce54803a9e6c72fc620feeab1278"]}