{"http://www.w3.org/1999/02/22-rdf-syntax-ns#type": ["http://www.w3.org/2002/07/owl#ObjectProperty", "http://www.w3.org/2002/07/owl#Class"], "http://www.w3.org/2000/01/rdf-schema#label": ["XE_Museum_Info"], "http://www.w3.org/2000/01/rdf-schema#range": ["http://www.xerleben.de/schema/2.0_1/XE_Museum_Info"], "http://www.w3.org/2000/01/rdf-schema#subClassOf": ["http://www.opengis.net/gml/3.2#AbstractObject", "http://www.xerleben.de/schema/2.0_1/Info"], "http://www.w3.org/2000/01/rdf-schema#subPropertyOf": ["http://www.xerleben.de/schema/2.0_1/XErleben2"], "http://www.w3.org/2004/02/skos/core#definition": ["Information zu der Frage, ob das Museum einen wesentlichen outdoor-Bestandteil hat bzw. ganz daraus besteht (Ja/Nein)."]}