{"http://www.w3.org/1999/02/22-rdf-syntax-ns#type": ["http://www.w3.org/2002/07/owl#Class"], "http://www.w3.org/2000/01/rdf-schema#label": ["Fotogeschaeft"], "http://www.w3.org/2000/01/rdf-schema#subClassOf": ["http://www.xerleben.de/schema/2.0_1/XE_Einzelhandel"], "http://www.w3.org/2002/07/owl#equivalentClass": ["nbfee3712af7a4fc2975d20adf8da8fcdb5366"], "http://www.w3.org/2004/02/skos/core#definition": ["Gesch\u00e4ft zum Verkauf von Fotoaparaten, Entwickeln von Fotos oder Anfertigung von Fotos durch einen Fotografen"], "http://www.wikidata.org/entity/Property:P18": ["http://www.xerleben.de/signaturen/2.8/standard/svg/72301440_XE_Einzelhandel_Fotogeschaeft.svg"], "http://www.xerleben.de/schema/2.0_1/code": ["72301440"], "http://www.xerleben.de/schema/2.0_1/sinceVersion": ["3.1"]}